MANIFEST.in
README.rst
setup.py
textfreq/__init__.py
textfreq/selectors.py
textfreq.egg-info/PKG-INFO
textfreq.egg-info/SOURCES.txt
textfreq.egg-info/dependency_links.txt
textfreq.egg-info/entry_points.txt
textfreq.egg-info/not-zip-safe
textfreq.egg-info/top_level.txt