Metadata-Version: 1.1
Name: textfreq
Version: 0.100
Summary: Count letters, letter pairs and words in text files. Also covers Devanagari and Bengali conjuncts
Home-page: http://github.com/m4rc1e/textfreq
Author: Marc Foley
Author-email: m.foley.88@gmail.com
License: MIT
Keywords: Letters,Letter Pairs,Non-Latin,non Latin,count,Devanagari,Bengali
Platform: UNKNOWN
Classifier: Development Status :: 3 - Alpha
Classifier: License :: OSI Approved :: MIT License
Classifier: Programming Language :: Python :: 2.7
Classifier: Topic :: Text Processing :: Linguistic
